flask_jsonvalidator/__init__.py
flask_jsonvalidator/flask_jsonvalidator.py
flask_jsonvalidator-1.0.4.dist-info/METADATA
flask_jsonvalidator-1.0.4.dist-info/WHEEL
flask_jsonvalidator-1.0.4.dist-info/top_level.txt
flask_jsonvalidator-1.0.4.dist-info/RECORD
