Metadata-Version: 2.1
Name: flask-jsonvalidator
Version: 1.0.4
Summary: Validates JSON data
Home-page: UNKNOWN
Author: Kenneth Gabriel
Author-email: kennethgabriel78@gmail.com
License: UNKNOWN
